boardgame2/__init__.py
boardgame2/env.py
boardgame2/go.py
boardgame2/kinarow.py
boardgame2/reversi.py
boardgame2-0.26.0.dist-info/METADATA
boardgame2-0.26.0.dist-info/WHEEL
boardgame2-0.26.0.dist-info/top_level.txt
boardgame2-0.26.0.dist-info/RECORD
