Metadata-Version: 2.1
Name: boardgame2
Version: 0.26.0
Summary: 2-player zero-sum board game extension for OpenAI Gym.
Home-page: http://github.com/zhiqingxiao/boardgame2/
Author: Zhiqing Xiao
Author-email: xzq.xiaozhiqing@gmail.com
Classifier: Development Status :: 5 - Production/Stable
Classifier: Programming Language :: Python
Classifier: Programming Language :: Python :: 3
Classifier: Intended Audience :: Developers
Classifier: Intended Audience :: Education
Classifier: Intended Audience :: Science/Research
Classifier: License :: Other/Proprietary License
Classifier: Operating System :: OS Independent
Classifier: Topic :: Games/Entertainment
Classifier: Topic :: Games/Entertainment :: Board Games
Requires-Python: >=3.9.0
Requires-Dist: six
Requires-Dist: numpy
Requires-Dist: gym (>=0.26)
